{
  "hyper-scrapper": [
    {
      "date": "2026-07-05T14:25:06.483859+00:00",
      "prix_min": 3.3,
      "nb_vendeurs": 87
    },
    {
      "date": "2026-07-07T06:04:23.537505+00:00",
      "prix_min": 6.89,
      "prix_moyen": 6.89,
      "nb_vendeurs": 86
    },
    {
      "date": "2026-07-08T14:22:36.489670+00:00",
      "prix_min": 6.89,
      "prix_moyen": 6.89,
      "nb_vendeurs": 87
    },
    {
      "date": "2026-07-12T06:34:52.690414+00:00",
      "prix_min": 6.89,
      "prix_moyen": 6.89,
      "nb_vendeurs": 87
    }
  ],
  "absorption-dome": [
    {
      "date": "2026-07-05T16:28:23.204118+00:00",
      "prix_min": 0.25,
      "nb_vendeurs": 357
    },
    {
      "date": "2026-07-07T07:01:18.608068+00:00",
      "prix_min": 0.25,
      "prix_moyen": 0.02,
      "nb_vendeurs": 352
    },
    {
      "date": "2026-07-12T07:01:19.183106+00:00",
      "prix_min": 0.25,
      "prix_moyen": 0.02,
      "nb_vendeurs": 368
    }
  ],
  "a-bit-off-the-side": [
    {
      "date": "2026-07-06T04:25:55.299370+00:00",
      "prix_min": 1.6,
      "prix_moyen": 1.99,
      "nb_vendeurs": 342
    },
    {
      "date": "2026-07-07T06:05:03.678569+00:00",
      "prix_min": 1.6,
      "prix_moyen": 2.42,
      "nb_vendeurs": 341
    },
    {
      "date": "2026-07-07T07:00:27.787777+00:00",
      "prix_min": 1.6,
      "prix_moyen": 2.42,
      "nb_vendeurs": 341
    },
    {
      "date": "2026-07-08T14:23:17.806041+00:00",
      "prix_min": 1.6,
      "prix_moyen": 2.54,
      "nb_vendeurs": 343
    },
    {
      "date": "2026-07-12T06:35:37.854473+00:00",
      "prix_min": 1.9,
      "prix_moyen": 2.63,
      "nb_vendeurs": 323
    },
    {
      "date": "2026-07-12T07:00:29.777537+00:00",
      "prix_min": 1.9,
      "prix_moyen": 2.63,
      "nb_vendeurs": 323
    }
  ],
  "a-good-clean-fight": [
    {
      "date": "2026-07-06T04:26:29.231725+00:00",
      "prix_min": 0.03,
      "prix_moyen": 0.02,
      "nb_vendeurs": 1118
    },
    {
      "date": "2026-07-07T06:05:35.846924+00:00",
      "prix_min": 0.03,
      "prix_moyen": 0.02,
      "nb_vendeurs": 1122
    },
    {
      "date": "2026-07-07T07:01:01.009331+00:00",
      "prix_min": 0.03,
      "prix_moyen": 0.02,
      "nb_vendeurs": 1122
    },
    {
      "date": "2026-07-12T06:36:11.928300+00:00",
      "prix_min": 0.02,
      "prix_moyen": 0.02,
      "nb_vendeurs": 1148
    },
    {
      "date": "2026-07-12T07:01:01.164925+00:00",
      "prix_min": 0.02,
      "prix_moyen": 0.02,
      "nb_vendeurs": 1148
    }
  ],
  "achilles-accelerator": [
    {
      "date": "2026-07-06T04:26:45.289108+00:00",
      "prix_min": 0.02,
      "prix_moyen": 0.06,
      "nb_vendeurs": 1636
    }
  ]
}